tests/__init__.py
tests/unit/__init__.py
tests/unit/test_wotapi.py
tests/unit/test_wrapper.py
tests/unit/action/__init__.py
tests/unit/action/test_access_token.py
tests/unit/action/test_account_id.py
tests/unit/action/test_base_action.py
tests/unit/action/test_player_achievements.py
tests/unit/action/test_player_personal_data.py
tests/unit/action/test_player_vehicles_data.py
tests/unit/action/test_tankopedia_achievements.py
tests/unit/action/test_tankopedia_badges.py
tests/unit/action/test_tankopedia_info.py
tests/unit/action/test_tankopedia_maps.py
tests/unit/action/test_tankopedia_vehicles.py
tests/unit/action/test_vehicles_achievements.py
tests/unit/action/test_vehicles_statistics.py
tests/unit/helper/__init__.py
tests/unit/helper/test_db_loader.py
tests/unit/helper/test_logger.py
tests/unit/helper/test_validators.py
tests/unit/models/__init__.py
tests/unit/models/test_models.py
tests/unit/orm/__init__.py
tests/unit/orm/test_orm_create_tables.py
tests/unit/orm/test_player_personal_achievements.py
tests/unit/orm/test_player_personal_data.py
tests/unit/orm/test_player_personal_vehicles.py
tests/unit/orm/test_tankopedia_achievements_model.py
tests/unit/orm/test_tankopedia_badges_model.py
tests/unit/orm/test_tankopedia_info_model.py
tests/unit/orm/test_tankopedia_maps_model.py
tests/unit/orm/test_tankopedia_vehicles_model.py
tests/unit/orm/test_vehicles_achievements_model.py
tests/unit/orm/test_vehicles_frags_model.py
tests/unit/orm/test_vehicles_statistics_model.py
tests/unit/utils/__init__.py
tests/unit/utils/test_api.py
wotapi/__init__.py
wotapi/wotapi.py
wotapi/action/__init__.py
wotapi/action/access_token.py
wotapi/action/account_id.py
wotapi/action/base_action.py
wotapi/action/player_achievements.py
wotapi/action/player_personal_data.py
wotapi/action/player_vehicles_data.py
wotapi/action/tankopedia_achievements.py
wotapi/action/tankopedia_badges.py
wotapi/action/tankopedia_info.py
wotapi/action/tankopedia_maps.py
wotapi/action/tankopedia_vehicles.py
wotapi-0.4.6.dist-info/LICENSE
wotapi-0.4.6.dist-info/METADATA
wotapi-0.4.6.dist-info/WHEEL
wotapi-0.4.6.dist-info/top_level.txt
wotapi-0.4.6.dist-info/RECORD
