Metadata-Version: 2.1
Name: wotapi
Version: 0.4.6
Summary: Extract data from the World of Tanks PC API
Home-page: https://github.com/gabriel-oana/wotapi
Author: Gabriel Oana
Author-email: gabriel.oana91@gmail.com
License: MIT
Classifier: Programming Language :: Python :: 3
Classifier: License :: OSI Approved :: MIT License
Classifier: Operating System :: OS Independent
Classifier: Topic :: Software Development :: Libraries :: Python Modules
Classifier: Typing :: Typed
Classifier: Programming Language :: Python :: 3.6
Classifier: Programming Language :: Python :: 3.7
Classifier: Programming Language :: Python :: 3.8
Classifier: Programming Language :: Python :: 3.9
Classifier: Programming Language :: Python :: 3.10
License-File: LICENSE
Requires-Dist: requests
Requires-Dist: sqlalchemy
